{ //this entity model, animations & textures was made by O2God for PFE
	"format_version": "1.10.0",
	"minecraft:client_entity": {
		"description": {
			"identifier": "poke:dragon",
			"materials": {
				"default": "entity_alphatest"
			},
			"textures": {
				"default": "textures/entity/dragon/poke_dragon_new",
				"is_saddled": "textures/entity/dragon/poke_dragon_saddled"
			},
			"geometry": {
				"default": "geometry.poke.dragon"
			},
			"animations": {
				"wing_off": "animation.poke.dragon.wing_off",
				"flying": "animation.poke.dragon.o2.flying",
				"controller":"controller.animation.poke.dragon.flying"
			},
			"render_controllers": [
				"controller.render.poke.dragon"
			],
			"scripts": {
				"animate": [
					"flying"
				]
			},
			"spawn_egg": {
				"base_color": "#6642c9",
				"overlay_color": "#7b608d"
			}
		}
	}
}